Workbook

Sheet 3000 with meanings
B1: level | C1: kelime | D1: anlami | E1: örnek cümle
B2: A1 | C2: above | D2: zf; üzerine, yukarıda, üstünde ,üzerinde s.; yukarıdaki, yukarıda geçen | E2: The birds were flying above the clouds. (Kuşlar bulutların üstünde uçuyorlardı.)
B3: A1 | C3: across | D3: f.; boydan boya geçmek ed.; karşısında zf.;karşıdan karşıya | E3: The hospital is right across the bank. (Hastane bankanın tam karşısında.)
B4: A1 | C4: action | D4: eylem, aksiyon, dava, fiil, davranış | E4: Everyone must take responsibility for their actions. (Herkes davranışlarının sorumluluğunu almalı.)
B5: A1 | C5: activity | D5: etkinlik, faaliyet, işlem, fiil | E5: The club provides a wide variety of activities. (Klüp çok çeşitli aktiviteler sunmaktadır.)
B6: A1 | C6: add | D6: eklemek, ilave etmek, katmak , toplamak | E6: Do you want to add your name to the list? (İsmini listeye eklemek ister misin)
B7: A1 | C7: arm | D7: i.; kol , güç, cephane f.; silahlandırmak , destek olmak | E7: She broke her arm in an accident. (Kazada kolunu kırdı.)
B8: A1 | C8: at | D8: zf.; üzere ed.;üzerinde, -de,-da | E8: I met him at school. (Onunla okulda karşılaştım.)
B9: A1 | C9: away | D9: s.; uzak, zf.; uzakta, | E9: She live 100 m away from here. (Buradan 100 metre uzakta yaşıyor.)
B10: A1 | C10: band | D10: i.; bando, müzik grubu ,bant , orkestra, şerit f.; bantlamak , bağlamak | E10: We bought ticket for the concert of the famous band.(Ünlü müzik grubunun konseri için bilet aldık.)
B11: A1 | C11: become | D11: olmak, haline gelmek | E11: She become a finance manager at a private bank .( Özel bir bankada finans müdürü oldu.)
B12: A1 | C12: behind | D12: s.; gerisindeki, ardındaki zf.; arkadan, geride ed.; ardında, arkasında | E12: The cat is standing just behind the window. (Kedi pencerenin hemen arkasında duruyor.)
... B1462: C1 | C1462: yield | D1462: i.; verim, getiri, mahsul f.; ürün vermek, kazanç sağlamak, boyun eğmek, teslim olmak | E1462: Rich soil yields good crops. (Zengin toprak iyi mahsul verir.)

Sheet Cumleler
B2: İngilizce Sözler: İngilizce Kısa, Anlamlı ve Güzel Sözler
B3: Written by Konuşarak Öğren in İngilizce Dersleri
B5: İngilizce Sözler
B6: Bu yazımızda sevdiklerinize gönderebileceğiniz, durumunuza yazabileceğiniz ve hatta hayatınızda size yol gösterebilecek İngilizce sözleri bulabilirsiniz. Güncellenmiş olan en anlamlı İngilizce sözler; karşınızda. Burada yer alan çeviriler; kolayca anlaşılması için özenle hazırlandı ve doğruluğu tekrar tekrar gözden geçirildi.
B7: Siz de sevdiklerinize İngilizce güzel sözler söylemek istiyorsanız doğru adrestesiniz. Üstelik buradaki içeriğimiz sürekli güncellenecek ve yeni kelimeler eklenecektir.
B8: Bir çok alanda özenle hazırlanmış İngilizce sözler listemizde İngilizce spor sözleri, İngilizce Tumblr sözleri, İngilizce komik ve eğlenceli sözler,İngilizce fotoğraf sözleri, gece ile ilgili İngilizce sözler, İngilizce hayat sözleri, İngilizce anneler günü sözleri, İngilizce kısa sözler, arkadaşlık, umut, özgürlük ile ilgili İngilizce sözler ve ünlü kişilerin İngilizce sözleri başlıklarında ihtiyacınız olan en güzel İngilizce sözlerine göz atabilirsiniz.
B9: Peki sevdiklerinize İngilizce aşk sözleri söylemek ister misiniz? Daha önce hazırladığımız İngilizce aşk sözlerini çevirileriyle birlikte mutlaka incelemelisiniz. İngilizce-Türkçe çevirisiyle hazırlanmış olan aşk sözleri de sürekli güncellenecektir.
B10: İngilizce güzel ve anlamlı sözler listemizdeki başlıkları aşağıdaki tablodan inceleyebilir ve başlığa tıklayarak ilgili bölüme hızlıca ulaşabilirsiniz. Üstelik sözlerimizin yanındaki buton ile İngilizce sözlerin telaffuzlarını da dinleyerek kendinizi geliştirebilirsiniz.
B11: Keyifli okumalar…
B13: İngilizce Kısa Sözler
B14: En güzel İngilizce kısa anlamlı sözler Türkçe açıklamalı aşağıdaki tablomuzda bulabilir, sesli telaffuzlarını dinleyebilir ve Türkçelerini öğrenebilirsiniz.
B15: Where there is love there is life. Aşkın olduğu yerde hayat vardır
... B144: A true friend is the greatest of all blessings: Gerçek arkadaş tüm nimetlerden kıymetlidir. Hard Times will always reveal true friends: Gerçek arkadaşlar zor zamanlarda belli olur. A good friend knows all your best stories. A best friend has lived them with you: İyi bir arkadaş tüm iyi anılarınızı bilir. En iyi arkadaş onları sizinle yaşar.

Sheet oxford 5000
B3: KELIME | C3: SEVIYE | D3: KARISIK TERCUME | E3: YDS TERCUME
B4: abandon | C4: B2 | D4: terk etmek, bırakmak, vazgeçmek, yüzüstü bırakmak | E4: =VLOOKUP(B4,'YDS Karisik'!C:D,2,0) -> bırakmak, terk etmek, vazgeçmek,
B5: ability | C5: A2 | D5: yetenek, beceri, kabiliyet, hüner | E5: =VLOOKUP(B5,'YDS Karisik'!C:D,2,0) -> yetenek, kabiliyet, capability, capacity,
B6: able | C6: A2 | D6: yetenekli, hünerli, yapabilen, becerikli,
B7: abolish | C7: C1 | D7: iptal etmek | E7: =VLOOKUP(B7,'YDS Karisik'!C:D,2,0) -> kaldırmak, feshetmek, cancel
B8: abortion | C8: C1 | D8: kürtaj, bebek aldırma, çocuk düşürme | E8: =VLOOKUP(B8,'YDS Karisik'!C:D,2,0) -> kürtaj
B9: about | C9: A1 | D9: üzere, yaklaşık, hemen hemen,aşağı yukarı, hakkında (ed.)
B10: above | C10: A1 | D10: zf; üzerine, yukarıda, üstünde ,üzerinde s.; yukarıdaki, yukarıda geçen
B11: abroad | C11: B2 | D11: zf.; yurt dışında s.; dışarı, dış ülke , yurt dışı | E11: =VLOOKUP(B11,'YDS Karisik'!C:D,2,0) -> yurt dışına, yurt dışında
B12: absence | C12: C1 | D12: bulunmama, yokluk, olmayış | E12: =VLOOKUP(B12,'YDS Karisik'!C:D,2,0) -> presence,
B13: absent | C13: C1 | D13: 1.yok 2.eksik | E13: =VLOOKUP(B13,'YDS Karisik'!C:D,2,0) -> namevcut, yok, unavailable,
B14: absolute | C14: B2 | D14: i. ;mutlak s.; salt,mutlak, kati, kesin | E14: =VLOOKUP(B14,'YDS Karisik'!C:D,2,0) -> 1) tam, halis, saf, mutlak, pure,
B15: absolutely | C15: B1 | D15: kesinlikle, mutlaka, tamamıyla, muhakkak | E15: =VLOOKUP(B15,'YDS Karisik'!C:D,2,0) -> tamamen, kesinlikle, totally, definitely
B16: absorb | C16: B2 | D16: emmek,içine çekmek, soğurmak, özümsemek, anlamak | E16: =VLOOKUP(B16,'YDS Karisik'!C:D,2,0) -> emmek, soğurmak, suck in, zıt anl.=
B17: abstract | C17: B2 | D17: soyut | E17: =VLOOKUP(B17,'YDS Karisik'!C:D,2,0) -> soyut, conceptual, intangible, zıt anl.=
B18: absurd | C18: C1 | D18: saçma
B19: abundance | C19: C1 | D19: bolluk | E19: =VLOOKUP(B19,'YDS Karisik'!C:D,2,0) -> bolluk, çokluk, zenginlik, copiousness,
B20: abuse | C20: C1 | D20: i.; suistimal, taciz f.; suistimal etmek, kötüye kullanmak, | E20: =VLOOKUP(B20,'YDS Karisik'!C:D,2,0) -> kötüye kullanmak, suiistimal etmek, misuse,
B21: academic | C21: B1 | D21: i.; öğretim görevlisi s.; akademik, bilimsel
B22: academy | C22: C1 | D22: akademi
B23: accelerate | C23: C1 | D23: hızlandırmak | E23: =VLOOKUP(B23,'YDS Karisik'!C:D,2,0) -> hızlan(dır)mak, ivme kazan(dır)mak,
B24: accent | C24: B2 | D24: şive, aksan
B25: accept | C25: A2 | D25: kabul etmek, kabullenmek, onaylamak
B26: acceptable | C26: B2 | D26: kabul edilebilir
B27: acceptance | C27: C1 | D27: kabul
B28: access | C28: B1 | D28: i.; erişme, erişim, giriş f.; erişmek,
B29: accessible | C29: C1 | D29: 1)içine girilebilinir 2)kolay bulunur | E29: =VLOOKUP(B29,'YDS Karisik'!C:D,2,0) -> ulaşılabilir, yararlanılabilir, available,
B30: accident | C30: A2 | D30: kaza , arıza, rastlantı, beklenmedik olay, kazara | E30: =VLOOKUP(B30,'YDS Karisik'!C:D,2,0) -> kaza
B31: accidentally | C31: B2 | D31: kazara | E31: =VLOOKUP(B31,'YDS Karisik'!C:D,2,0) -> kazara, yanlışlıkla, tesadüfen
B32: accommodate | C32: B2 | D32: yerleştirmek | E32: =VLOOKUP(B32,'YDS Karisik'!C:D,2,0) -> 1) yer / yaşam alanı sağlamak, be
B33: accompany | C33: B2 | D33: eşlik etmek, yanında olmak, , arkadaşlık etmek, yoldaşlık etmek | E33: =VLOOKUP(B33,'YDS Karisik'!C:D,2,0) -> eşlik etmek, (bir şey)’in beraberinde
B34: accomplish | C34: B2 | D34: başarıyla tamamlamak, becermek, sonuçlandırmak, üstesinden gelmek
B35: accomplishment | C35: C1 | D35: başarı | E35: =VLOOKUP(B35,'YDS Karisik'!C:D,2,0) -> başarı, üstesinden gelme,
B36: accordance | C36: C1 | D36: uygun
B37: according | C37: A2 | D37: i.; uyma f.; uyarak, uygun olarak, -e göre, birseye bagli olarak
B38: accordingly | C38: C1 | D38: buna göre | E38: =VLOOKUP(B38,'YDS Karisik'!C:D,2,0) -> dolayısıyla, bu nedenle, so,
B39: account | C39: B2 | D39: i.; hesap , hesap verme f.; açıklamak, hesap vermek, saymak
B40: accountability | C40: C1 | D40: Hesap verebilirlik
B41: accountable | C41: C1 | D41: sorumlu
B42: accountant | C42: B2 | D42: Muhasebeci
B43: accumulate | C43: C1 | D43: toplamak,biriktirmek | E43: =VLOOKUP(B43,'YDS Karisik'!C:D,2,0) -> topla(n)mak, yığ(ıl)mak, birik(tir)mek,
B44: accumulation | C44: C1 | D44: birikim | E44: =VLOOKUP(B44,'YDS Karisik'!C:D,2,0) -> birikme, birikinti
B45: accuracy | C45: B2 | D45: kesinlik | E45: =VLOOKUP(B45,'YDS Karisik'!C:D,2,0) -> doğruluk, kesinlik, precision, exactness,
B46: accurate | C46: B2 | D46: kesin, doğru, tam, hatasız, dakik | E46: =VLOOKUP(B46,'YDS Karisik'!C:D,2,0) -> doğru, titiz, eksiksiz, precise, zıt anl.=
B47: accurately | C47: B2 | D47: doğruca | E47: =VLOOKUP(B47,'YDS Karisik'!C:D,2,0) -> doğru, tam (olarak), correctly, exactly,
B48: accusation | C48: C1 | D48: suçlama
B49: accuse | C49: B2 | D49: suçlamak, suçlamada bulunmak, itham etmek
B50: accused | C50: C1 | D50: 1)sanik 2)suçlamak | E50: =VLOOKUP(B50,'YDS Karisik'!C:D,2,0) -> sanık
B51: achieve | C51: A2 | D51: başarmak, elde etmek, ulaşmak, üstesinden gelmek | E51: =VLOOKUP(B51,'YDS Karisik'!C:D,2,0) -> başarmak, (zorlu bir uğraştan sonra) elde
B52: achievement | C52: B1 | D52: başarı, başarma, elde etme,kazanım | E52: =VLOOKUP(B52,'YDS Karisik'!C:D,2,0) -> başarı, elde etme, kazanma,
B53: acid | C53: C1 | D53: i.; asit, ekşime s.; ekşi
B54: acknowledge | C54: B2 | D54: kabul etmek, kabullenmek, tasdik etmek, beyan etmek | E54: =VLOOKUP(B54,'YDS Karisik'!C:D,2,0) -> (bir gerçeği) kabul etmek, bildirmek,
B55: acquire | C55: B2 | D55: elde etmek, edinmek, kazanmak, sahip olmak | E55: =VLOOKUP(B55,'YDS Karisik'!C:D,2,0) -> elde etmek, kazanmak, obtain, gain, zıt
B56: acquisition | C56: C1 | D56: edinme, istimlak, el koyma | E56: =VLOOKUP(B56,'YDS Karisik'!C:D,2,0) -> elde etme, sahip olma, gain, earning
B57: acre | C57: C1 | D57: dönüm
B58: across | C58: A1 | D58: f.; boydan boya geçmek ed.; karşısında zf.;karşıdan karşıya | E58: =VLOOKUP(B58,'YDS Karisik'!C:D,2,0) -> 1) karşısına, diğer yakasına, to the other
B59: act | C59: B1 | D59: f.; davranmak, hareket etmek, rol oynamak, yalandan yapmak i.; yasa, eylem | E59: =VLOOKUP(B59,'YDS Karisik'!C:D,2,0) -> 1) yasa; 2) (tiyatroda) perde; 3) hareket, eylem
B60: action | C60: A1 | D60: eylem, aksiyon, dava, fiil, davranış | E60: =VLOOKUP(B60,'YDS Karisik'!C:D,2,0) -> inaction; 2) etki,
B61: activate | C61: B2 | D61: etkinleştirmek
B62: activation | C62: C1 | D62: aktivasyon | E62: =VLOOKUP(B62,'YDS Karisik'!C:D,2,0) -> harekete geçirme
B63: active | C63: A2 | D63: etkin, faal, aktif, çalışkan
B64: activist | C64: C1 | D64: aktivist, eylemci
B65: activity | C65: A1 | D65: etkinlik, faaliyet, işlem, fiil | E65: =VLOOKUP(B65,'YDS Karisik'!C:D,2,0) -> faaliyet, etkinlik
B66: actor | C66: A1 | D66: oyuncu, erkek oyuncu, aktör,artist,
B67: actress | C67: A1 | D67: oyuncu, kadın oyuncu, aktris, artist
B68: actual | C68: B2 | D68: asıl, gerçek, hakiki, doğru, aktüel
B69: actually | C69: A2 | D69: aslında, fiilen, gerçekte, sahiden | E69: =VLOOKUP(B69,'YDS Karisik'!C:D,2,0) -> aslında, gerçekten, aslına bakılırsa, as a
B70: acute | C70: C1 | D70: akut | E70: =VLOOKUP(B70,'YDS Karisik'!C:D,2,0) -> 1) ağır, vahim; 2) akut, hızlı seyreden /
B71: ad | C71: B1 | D71: reklam, ilan, duyuru *advertisement
B72: adapt | C72: B2 | D72: adapte etmek, adapte olmak, uyarlamak, uymak, uyum sağlamak
B73: adaptation | C73: C1 | D73: uyarlama | E73: =VLOOKUP(B73,'YDS Karisik'!C:D,2,0) -> adaptasyon, uyum
B74: add | C74: A1 | D74: eklemek, ilave etmek, katmak , toplamak
B75: addiction | C75: B2 | D75: bağımlılık
B76: addition | C76: B1 | D76: ek, ekleme, ilave, toplama, katma , eklenti
B77: additional | C77: B2 | D77: ek , ilave, ilaveten | E77: =VLOOKUP(B77,'YDS Karisik'!C:D,2,0) -> ek, fazladan, extra
B78: additionally | C78: B2 | D78: bunlara ek olarak | E78: =VLOOKUP(B78,'YDS Karisik'!C:D,2,0) -> ek olarak, in addition, also
B79: address | C79: B2 | D79: f.; hitap etmek, konuşma yapmak, göndermek, değinmek, adres yazmak i.; adres, söylev, hitap, konuşma, speech | E79: =VLOOKUP(B79,'YDS Karisik'!C:D,2,0) -> (bir şey)’e değinmek, (bir şey) ile
B80: adequate | C80: B2 | D80: yeterli, uygun, kafi | E80: =VLOOKUP(B80,'YDS Karisik'!C:D,2,0) -> yeterli, enough, sufficient, zıt anl.=
B81: adequately | C81: B2 | D81: yeterince | E81: =VLOOKUP(B81,'YDS Karisik'!C:D,2,0) -> yeterince, yeterli bir biçimde / oranda,
B82: adhere | C82: C1 | D82: uymak
B83: adjacent | C83: C1 | D83: bitişik | E83: =VLOOKUP(B83,'YDS Karisik'!C:D,2,0) -> yan yana, bitişik
B84: adjust | C84: B2 | D84: ayarlamak, uydurmak, uyarlamak, adapte olmak | E84: =VLOOKUP(B84,'YDS Karisik'!C:D,2,0) -> confuse,
B85: adjustment | C85: C1 | D85: ayar, ayarlama, uydurma, düzenleme, adaptasyon | E85: =VLOOKUP(B85,'YDS Karisik'!C:D,2,0) -> ayarlama, adapte olma / etme,
B86: administer | C86: C1 | D86: idare etmek | E86: =VLOOKUP(B86,'YDS Karisik'!C:D,2,0) -> (ilaç vs.) vermek
B87: administration | C87: B1 | D87: yönetim, idare, yöneticilik, idarecilik | E87: =VLOOKUP(B87,'YDS Karisik'!C:D,2,0) -> 1) idare; 2) (ilaç) verme / uygulama
B88: administrative | C88: C1 | D88: Yönetim
B89: administrator | C89: C1 | D89: yönetici, idareci, müdür, | E89: =VLOOKUP(B89,'YDS Karisik'!C:D,2,0) -> yönetici, idareci
B90: admire | C90: B1 | D90: hayran olmak, beğenmek, | E90: =VLOOKUP(B90,'YDS Karisik'!C:D,2,0) -> takdir etmek, beğenmek, hayran olmak,
B91: admission | C91: C1 | D91: itiraf, kabul, giriş izni, teslim | E91: =VLOOKUP(B91,'YDS Karisik'!C:D,2,0) -> 1) kabul etme, acceptance, zıt anl.=
B92: admit | C92: B1 | D92: itiraf etmek, kabul etmek, izin vermek, teslim etmek | E92: =VLOOKUP(B92,'YDS Karisik'!C:D,2,0) -> itiraf etmek, kabul etmek, (gelmesine,
B93: adolescent | C93: C1 | D93: s.; ergen, ergenlik çağında olan, genç i.; yeni yetme, delikanlı | E93: =VLOOKUP(B93,'YDS Karisik'!C:D,2,0) -> ergen
B94: adopt | C94: B2 | D94: evlat edinmek, benimsemek, kabul etmek, sahiplenmek | E94: =VLOOKUP(B94,'YDS Karisik'!C:D,2,0) -> 1) benimsemek, accept, assume, zıt anl.=
B95: adoption | C95: C1 | D95: Benimseme | E95: =VLOOKUP(B95,'YDS Karisik'!C:D,2,0) -> 1) evlat edinme; 2) (fikir, ideoloji, vs.)
B96: adult | C96: A2 | D96: i.; yetişkin s.; ergin, yetişkin | E96: =VLOOKUP(B96,'YDS Karisik'!C:D,2,0) -> yetişkin
B97: advance | C97: B2 | D97: f.; ilerlemek, geliştirmek, gelişim göstermek i.; ilerleme, terfi | E97: =VLOOKUP(B97,'YDS Karisik'!C:D,2,0) -> ilerlemek, gelişmek, progress, develop, zıt
B98: advanced | C98: B1 | D98: ileri, gelişmiş, ileri derecede | E98: =VLOOKUP(B98,'YDS Karisik'!C:D,2,0) -> gelişmiş, ileri düzeyde
B99: advantage | C99: A2 | D99: yarar, fayda, avantaj, | E99: =VLOOKUP(B99,'YDS Karisik'!C:D,2,0) -> avantaj, üstünlük sağlayan şey, yarar,
B100: adventure | C100: A2 | D100: i.; macera , serüven, risk f.; tehlikeye atmak, riske atmak | E100: =VLOOKUP(B100,'YDS Karisik'!C:D,2,0) -> macera, serüven
... B106: advise | C106: B1 | D106: öğüt vermek, nasihat etmek, tavsiyede bulunmak, danışmak | E106: =VLOOKUP(B106,'YDS Karisik'!C:D,2,0) -> öğüt vermek, tavsiyede bulunmak, counsel,
B107: advocate | C107: C1 | D107: i.; avukat, savunucu f.; desteklemek, müdafaa etmek , savunmak
...

Sheet 3600
B2: Abandon | C2: ebandın | D2: terk etmek | E2: =VLOOKUP(B2,'oxford 5000'!B:C,2,0) -> B2
B3: Ability | C3: ebılıti | D3: yetenek | E3: =VLOOKUP(B3,'oxford 5000'!B:C,2,0) -> A2
B4: Able | C4: eybıl | D4: muktedir | E4: =VLOOKUP(B4,'oxford 5000'!B:C,2,0) -> A2
B5: Aboard | C5: ebord | D5: (bir taşıtın)içinde olmak | E5: =VLOOKUP(B5,'oxford 5000'!B:C,2,0) -> #N/A
B6: About | C6: ebaut | D6: 1.hakkinda 2.yaklaşik olarak | E6: =VLOOKUP(B6,'oxford 5000'!B:C,2,0) -> A1
B7: Above | C7: ebav | D7: yukaridaki | E7: =VLOOKUP(B7,'oxford 5000'!B:C,2,0) -> A1
B8: Abroad | C8: ebrod | D8: yurt dişi | E8: =VLOOKUP(B8,'oxford 5000'!B:C,2,0) -> B2
B9: Absence | C9: ebsıns | D9: yokluk | E9: =VLOOKUP(B9,'oxford 5000'!B:C,2,0) -> C1
B10: Absent | C10: ebsınt | D10: 1.yok 2.eksik | E10: =VLOOKUP(B10,'oxford 5000'!B:C,2,0) -> C1
B11: Absolute | C11: ebsolut | D11: mutlak, kesin | E11: =VLOOKUP(B11,'oxford 5000'!B:C,2,0) -> B2
B12: Absurd | C12: ebzörd | D12: saçma | E12: =VLOOKUP(B12,'oxford 5000'!B:C,2,0) -> C1
B13: Accept | C13: eksept | D13: kabul etmek | E13: =VLOOKUP(B13,'oxford 5000'!B:C,2,0) -> A2
... B3627: What If | C3627: wat if | D3627: ne olurdu.. | E3627: =VLOOKUP(B3627,'oxford 5000'!B:C,2,0) -> #N/A
B3628: What's Its (His/Her) Name | D3628: bilmem kim (birisinin adini unutma) | E3628: =VLOOKUP(B3628,'oxford 5000'!B:C,2,0) -> #N/A
B3629: What's More | C3629: wats mor | D3629: bunun yanisira, üstelik | E3629: =VLOOKUP(B3629,'oxford 5000'!B:C,2,0) -> #N/A
B3630: What's What | C3630: wats wat | D3630: işin önemini bilmek (i know what's what) | E3630: =VLOOKUP(B3630,'oxford 5000'!B:C,2,0) -> #N/A
B3631: Wheel | C3631: wiil | D3631: tekerlek, çark, tekerlekli bir şeyi elle itmek | E3631: =VLOOKUP(B3631,'oxford 5000'!B:C,2,0) -> A2
B3632: Whim | C3632: whim | D3632: kapris | E3632: =VLOOKUP(B3632,'oxford 5000'!B:C,2,0) -> #N/A
B3633: Whisper | C3633: wispır | D3633: fisildamak, fisildaşmak | E3633: =VLOOKUP(B3633,'oxford 5000'!B:C,2,0) -> B2
B3634: Wind Screen | C3634: wind skriin | D3634: araba ön cami | E3634: =VLOOKUP(B3634,'oxford 5000'!B:C,2,0) -> #N/A
B3635: Windpipe | C3635: windpayp | D3635: nefes borusu | E3635: =VLOOKUP(B3635,'oxford 5000'!B:C,2,0) -> #N/A
B3636: Windscreen Wiper | C3636: windskriin way | D3636: silecek | E3636: =VLOOKUP(B3636,'oxford 5000'!B:C,2,0) -> #N/A
B3637: Wing | C3637: wing | D3637: kanat (kuş,uçak)(left wing:sol kesimi destekleyenler | E3637: =VLOOKUP(B3637,'oxford 5000'!B:C,2,0) -> B1
B3638: Wisdom | C3638: wizdım | D3638: akil | E3638: =VLOOKUP(B3638,'oxford 5000'!B:C,2,0) -> B2
B3639: Witch | C3639: wiρ | D3639: cadi | E3639: =VLOOKUP(B3639,'oxford 5000'!B:C,2,0) -> #N/A
B3640: Worship | C3640: wörşip | D3640: 1)tapmak, tapinmak, ibadet 2)hayranlik, saygi | E3640: =VLOOKUP(B3640,'oxford 5000'!B:C,2,0) -> C1
... B3642: Zoom | C3642: zum | D3642: yaklaştirmak | E3642: =VLOOKUP(B3642,'oxford 5000'!B:C,2,0) -> #N/A

Sheet YDS Karisik
B2: a broad range = geniş bir alan / yelpaze | C2: a broad range | D2: geniş bir alan / yelpaze
B3: a case in point = iyi bir örnek | C3: a case in point | D3: iyi bir örnek
B4: a change of air = hava değişimi | C4: a change of air | D4: hava değişimi
B5: a couple of = birkaç, iki üç, a few | C5: a couple of | D5: birkaç, iki üç, a few
B6: a day out in the country = dışarıda kırlarda | C6: a day out in the country | D6: dışarıda kırlarda geçirilen bir gün
B7: a desperate situation = vahim bir durum | C7: a desperate situation | D7: vahim bir durum
B8: a far from pleasant place to live = yaşamak için | C8: a far from pleasant place to live | D8: yaşamak için
B9: iyi / hoş bir yer olmaktan uzak | C9: iyi / hoş bir | D9: bir yer olmaktan uzak
B10: a full recovery = tam bir iyileşme / düzelme | C10: a full recovery | D10: tam bir iyileşme / düzelme
B11: a good many = birçok, hayli, a large number of | C11: a good many | D11: birçok, hayli, a large number of
B12: a great deal (of) = oldukça fazla, çok, a lot, much, | C12: a great deal (of) | D12: oldukça fazla, çok, a lot, much,
B13: zıt anl.= a little, a bit | C13: zıt anl.= a | D13: a little, a bit
B14: a large number (of) = birçok, hayli, a good many, | C14: a large number (of) | D14: birçok, hayli, a good many,
B15: a lot (of) | C15: a lot (of
B16: a major step forward = ileriye doğru büyük bir adım | C16: a major step forward | D16: ileriye doğru büyük bir adım
B17: a matter of time = an meselesi | C17: a matter of time | D17: an meselesi
B18: a number of = çok sayıda, (belli) bir miktar, a lot of, | C18: a number of | D18: çok sayıda, (belli) bir miktar, a lot of,
B19: plenty of
B20: a painful cut in pay = maaşlarda büyük bir kesinti | C20: a painful cut in pay | D20: maaşlarda büyük bir kesinti
B21: a range of = 1) çeşitli, various; 2) bir dizi, a series of | C21: a range of | D21: 1) çeşitli, various; 2) bir dizi, a series of
B22: a series of = bir dizi, a range of | C22: a series of | D22: bir dizi, a range of
B23: a series of measures = bir dizi önlem / tedbir | C23: a series of measures | D23: bir dizi önlem / tedbir
B24: a sociallyminded urban style = sosyal kaygılar | C24: a sociallyminded urban style | D24: sosyal kaygılar
B25: güden bir kentleşme biçimi | C25: güden bir kentleşme | D25: güden bir kentleşme biçimi
B26: a sure sign (of) = (bir şey)’in kesin bir işareti / | C26: a sure sign (of) | D26: (bir şey)’in kesin bir işareti /
B27: göstergesi
B28: a variety of = bir dizi, a range of | C28: a variety of | D28: bir dizi, a range of
B29: a whole range of = her çeşit, her tür, çok çeşitli | C29: a whole range of | D29: her çeşit, her tür, çok çeşitli
B30: a wide range of reasons = çok çeşitli sebepler | C30: a wide range of reasons | D30: çok çeşitli sebepler
B31: A. D. = Milattan / İsa’dan sonra, anno Domini, zıt | C31: A. D. | D31: Milattan / İsa’dan sonra, anno Domini, zıt
B32: anl.= B. C. , before Christ | C32: anl.= B. C | D32: B. C. , before Christ
B33: abandon = bırakmak, terk etmek, vazgeçmek, | C33: abandon | D33: bırakmak, terk etmek, vazgeçmek,
B34: discontinue, stop, zıt anl.= pursue, carry on | C34: discontinue, stop, zıt | D34: pursue, carry on
B35: abandoned = terk edilmiş, boş, (bina için) viran | C35: abandoned | D35: terk edilmiş, boş, (bina için) viran
B36: halde, desolate, zıt anl.= occupied | C36: halde, desolate, zıt | D36: occupied
B37: abandonment = terk etme / edilme, bırak(ıl)ma, | C37: abandonment | D37: terk etme / edilme, bırak(ıl)ma,
B38: desertion
B39: abate = azal(t)mak, hızını kesmek, die away, | C39: abate | D39: azal(t)mak, hızını kesmek, die away,
B40: diminish, zıt anl.= amplify, intensify | C40: diminish, zıt anl | D40: amplify, intensify
B41: abbreviation = kısaltma | C41: abbreviation | D41: kısaltma
B42: abdominal fat = karın bölgesindeki yağ | C42: abdominal fat | D42: karın bölgesindeki yağ
B43: aberrant = sapkın, anormal, abnormal | C43: aberrant | D43: sapkın, anormal, abnormal
B44: aberration = anormallik, sapma | C44: aberration | D44: anormallik, sapma
B45: ability = yetenek, kabiliyet, capability, capacity, | C45: ability | D45: yetenek, kabiliyet, capability, capacity,
B46: zıt anl.= inadequacy, limitation | C46: zıt anl.= inadequacy | D46: inadequacy, limitation
B47: ablution = abdest | C47: ablution | D47: abdest
B48: abnormal brain scan = beyin taramasında (ortaya | C48: abnormal brain scan | D48: beyin taramasında (ortaya
B49: çıkan) anormallik | C49: çıkan) anorma | D49: k
B50: abnormally = anormal şekilde, alışılmışın dışında, | C50: abnormally | D50: anormal şekilde, alışılmışın dışında,
B51: unusually
B52: aboard = (gemi, uçak, tren gibi taşıtlar için) içine, | C52: aboard | D52: (gemi, uçak, tren gibi taşıtlar için) içine, içinde
B53: abolish = kaldırmak, feshetmek, cancel | C53: abolish | D53: kaldırmak, feshetmek, cancel
B54: abolition = (ortadan) kaldırma, ilga, fesih, | C54: abolition | D54: (ortadan) kaldırma, ilga, fesih, cancellation, repulsion
B55: abominably = rahatsız edici bir şekilde, dreadfully | C55: abominably | D55: rahatsız edici bir şekilde, dreadfully
B56: abort = çocuk düşürmek, gebeliği sonlandırmak | C56: abort | D56: çocuk düşürmek, gebeliği sonlandırmak
B57: abortion = kürtaj | C57: abortion | D57: kürtaj
B58: abound in / with = (bir şey)’i bolca / çokça | C58: abound in / with | D58: (bir şey)’i bolca / çokça
B59: bulundurmak / içermek, be abundant with, | C59: bulundurmak / içermek, be | D59: içermek, be abundant with,
B60: zıt anl.= be lacking, be short of | C60: zıt anl.= be | D60: be lacking, be short of
B61: above all = hepsinden ziyade, en başta, mostly | C61: above all | D61: hepsinden ziyade, en başta, mostly
B62: abrasion = sıyrık, soyulma veya kazınma, aşınma | C62: abrasion | D62: sıyrık, soyulma veya kazınma, aşınma
B63: abroad = yurt dışına, yurt dışında | C63: abroad | D63: yurt dışına, yurt dışında
B64: abrupt = 1) ani, beklenmedik, ani ve kaba, sudden; | C64: abrupt | D64: 1) ani, beklenmedik, ani ve kaba, sudden;
B65: 2) dik, sarp | C65: 2) dik, sarp
B66: abruptly = aniden, birdenbire, ani ve kaba bir şekilde, | C66: abruptly | D66: aniden, birdenbire, ani ve kaba bir şekilde,
B67: suddenly, (The talks ended abruptly when one | C67: suddenly, (The talks | D67: ended abruptly when one
B68: of the delegations walked out in protest. = | C68: of the delegations walked out in protest. | D68: walked out in protest. =
B69: Delegelerden biri protesto amacıyla salonu | C69: Delegelerden biri protesto | D69: biri protesto amacıyla salonu
B70: terk edince görüşmeler aniden kesildi.) | C70: terk edince görüşmeler | D70: edince görüşmeler aniden kesildi.)
B71: absence = yokluk, bulunmama, zıt anl.= presence, | C71: absence | D71: presence,
B72: existence
B73: absence of empathy = empati eksikliği (kendini | C73: absence of empathy | D73: empati eksikliği (kendini
B74: karşısındakinin yerine koyabilme yetisinin | C74: karşısındakinin yerine koyabilme | D74: karşısındakinin yerine koyabilme yetisinin
B75: eksikliği)
B76: absent = namevcut, yok, unavailable, | C76: absent | D76: namevcut, yok, unavailable,
B77: zıt anl.= present, available | C77: zıt anl.= present | D77: present, available
B78: absolute = 1) tam, halis, saf, mutlak, pure, | C78: absolute | D78: 1) tam, halis, saf, mutlak, pure,
B79: zıt anl.= imperfect; 2) (bir şey)’in hepsi, | C79: zıt anl.= imperfect | D79: imperfect; 2) (bir şey)’in hepsi,
B80: tamamı, complete, zıt anl.= limited | C80: tamamı, complete, zıt | D80: limited
B81: absolute temperature = mutlak sıcaklık (Kelvin | C81: absolute temperature | D81: mutlak sıcaklık (Kelvin
B82: biriminde ölçülen sıcaklık) | C82: biriminde ölçülen sıcaklık | D82: n sıcaklık)
B83: absolute zero = mutlak sıfır (0°K’ye ve -273°C’ye | C83: absolute zero | D83: mutlak sıfır (0°K’ye ve -273°C’ye
B84: eşit, olası en düşük sıcaklık) | C84: eşit, olası en | D84: olası en düşük sıcaklık)
B85: absolutely = tamamen, kesinlikle, totally, definitely | C85: absolutely | D85: tamamen, kesinlikle, totally, definitely
B86: A A A A A | C86: A A A | D86: A A A A
B87: 4 - YDS Kelimeleri Sözlüğü | C87: 4 - YDS Kelimeleri Sözlüğü | D87: 4 - YDS Kelimeleri Sözlüğü
B88: www.bademci.com | C88: www.bademci.com
B89: absorb = emmek, soğurmak, suck in, zıt anl.= | C89: absorb | D89: emmek, soğurmak, suck in, zıt anl.=
B90: discharge, emit | C90: discharge, em
B91: absorption = em(il)me, soğur(ul)ma, bütünleşme, | C91: absorption | D91: em(il)me, soğur(ul)ma, bütünleşme,
B92: kaynaşma
B93: abstract = soyut, conceptual, intangible, zıt anl.= | C93: abstract | D93: soyut, conceptual, intangible, zıt anl.=
B94: concrete, actual | C94: concrete, act
B95: abundance = bolluk, çokluk, zenginlik, copiousness, | C95: abundance | D95: bolluk, çokluk, zenginlik, copiousness,
B96: wealth, zıt anl.= scarcity | C96: wealth, zıt anl | D96: scarcity
B97: abundant = bol, bereketli, ample, zıt anl.= scarce, | C97: abundant | D97: scarce,
B98: inadequate
B99: abundantly = bolca, büyük miktarda, copiously, | C99: abundantly | D99: bolca, büyük miktarda, copiously,
B100: profusely, zıt anl.= rarely, scarcely | C100: profusely, zıt anl | D100: rarely, scarcely
B101: abuse = kötüye kullanmak, suiistimal etmek, misuse, | C101: abuse | D101: kötüye kullanmak, suiistimal etmek, misuse,
...

Sheet 16000
B1: Word | C1: turkish meaning of below words
A2: 1 | B2: (it's well) worth it | C2: buna değer
A3: 2 | B3: a bit more | C3: biraz daha fazla
A4: 3 | B4: a bunch of | C4: bir grup
A5: 4 | B5: a clear conscience | C5: gönül rahatlığı
A6: 5 | B6: a dithering idiot | C6: sarsak
A7: 6 | B7: A Few | C7: az sayıda
A8: 7 | B8: a good deal of | C8: bir damla,birçok
A9: 8 | B9: A Great Many | C9: pek çok , çok fazla
A10: 9 | B10: a leg up | C10: destek,koltuk çıkma
A11: 10 | B11: a little way off | C11: biraz uzakta
A12: 11 | B12: a long way off | C12: çok uzak,çok uzakta
A13: 12 | B13: a modicum of | C13: zerre kadar,az bir miktar
... A16001: 15698 | B16001: wench | C16001: hizmetçi kız

Sheet İdiom
A1: Idioms
A2: sıra | B2: kelime | C2: türkçesi | D2: sıra | E2: kelime | F2: türkçesi
A3: 1 | B3: a bean counter | C3: (aşağılayıcı anlamda) muhasebeci | D3: 248 | E3: huff and puff | F3: burnundan solumak, öfleyip pöflemek
A4: 2 | B4: a bee in one's bonnet | C4: bir konuya kafasını takmak | D4: 249 | E4: I could eat a horse | F4: kurt gibi açım
A5: 3 | B5: a big-head | C5: ukala, bilmiş | D5: 250 | E5: if push comes to shove | F5: iş o noktaya gelirse
A6: 4 | B6: a bit under the weather | C6: kendini kötü hissetmek | D6: 251 | E6: in a black mood | F6: kötü ruh hali
B7: a center of interest | C7: ilgi merkezi | D7: 252 | E7: in a constant state of flux | F7: sürekli değişen, değişmekte
A8: 5 | B8: a chunk of change | C8: büyük/çok para | D8: 253 | E8: in a pinch | F8: gerektiğinde, sıkışınca
A9: 6 | B9: a cog in the machine | C9: çarkın dişlisi, sistemin işlemesini sağlayan küçük bir parça | D9: 254 | E9: in any event | F9: ne olursa olsun, her halükarda
A10: 7 | B10: a cold fish | C10: soguk,arkadaşça olmayan | D10: 255 | E10: in dribs and drabs | F10: azar azar
A11: 8 | B11: a face as long as a fiddle | C11: çok üzgün görünen | D11: 256 | E11: in fine fettle | F11: keyfi yerinde.
A12: 9 | B12: a good turn | C12: bir iyilik: arkadaşça davranış | D12: 257 | E12: in for a penny in for a pound | F12: kaybedecek bir şey yok, battı balık yan gider
A13: 10 | B13: a heart of gold | C13: altın gibi kalbi olmak | D13: 258 | E13: in full swing | F13: en yoğun döneminde, tam faaliyet halinde
A14: 11 | B14: a heavy hitter | C14: ağır top | D14: 259 | E14: in high dudgeon | F14: hiddetli.siniri tepesinde
A15: 12 | B15: a red-letter day | C15: önemli/özel gün | D15: 260 | E15: in high spirits | F15: sevinçli,neşeli
A16: 13 | B16: a shot across the bow | C16: uyarı ateşi,uyarı | D16: 261 | E16: in one fell swoop | F16: bir hamlede.bir çırpıda
A17: 14 | B17: a skeleton in the cupboard | C17: aile sırrı ,kirli çamaşır | D17: 262 | E17: in one's heart of hearts | F17: kalbinin derinliklerinde.tüm kalbiyle
A18: 15 | B18: a whole nother thing | C18: tamamen başka bir şey,tümüyle apayrı bir şey | D18: 263 | E18: in someone's stead | F18: birinin namına, birinin yerine
A19: 16 | B19: abound in\with | C19: (bir yerde) bol olmak, çok olmak. | D19: 264 | E19: in the blink of an eye | F19: göz açıp kapayana kadar
... A55: 47 | B55: be on the warpath | C55: burnundan solumak, küplere binmek | D55: 301 | E55: let in on | F55: birine gizli/herkesin bilmediği bir sırrı açıklamak
B56: be on to someone | C56: (birinin) ne numara çevirdiğini anlamak | D56: 302 | E56: let off the hook | F56: zor durumdan kurtarmak, sorundan kurtarmak
A57: 48 | B57: be out for blood | C57: intikam istemek/aramak | D57: 303 | E57: let out | F57: kaçmasına izin vermek, (bilgi vb) dışarı sızdırmak
A58: 49 | B58: be out of keeping with | C58: (bir şeye) uygun olmamak, garip kaçmak | D58: 304 | E58: let the cat out of the bag | F58: ağzındaki baklayı çıkarmak, bir sırrı açıklamak
A59: 50 | B59: be up and about | C59: tekrar eski haline gelmek, (hastalıktan) kalkmak | D59: 305 | E59: let the dead bury dead | F59: geçmişe sünger çek
A60: 51 | B60: be well in with | C60: arkadaşlık kurmak, insanlarla iyi ilişkiler kurmak | D60: 306 | E60: lie fallow | F60: boş kalmak, (yetenek) (uzun süredir) kullanılmamak
A61: 52 | B61: bear in mind | C61: unutma | D61: 307 | E61: lie low | F61: gizlenmek, saklanmak.
A62: 53 | B62: beat about the bush | C62: bin dereden su getirmek, sözü ağzında gevelemek | D62: 308 | E62: lie through one's teeth | F62: bir ayak üstünde bin yalan söylemek, adamın gözünün içine baka baka yalan söylemek
A63: 54 | B63: bide one's time | C63: (bir iş için) uygun zamanı beklemek | D63: 309 | E63: like a bear with sore head | F63: sinirli,huysuz,sol tarafından kalkmış
A64: 55 | B64: big-shot | C64: önemli kimse,kodoman | D64: 310 | E64: lion's share of something | F64: bir şeyin aslan payı
A65: 56 | B65: bit off | C65: bir tahtası eksik, hafif kaçık | D65: 311 | E65: live on the edge | F65: hayatı uçlarda yaşamak
B66: black sheep of the family | C66: ailenin yüz karası | D66: 312 | E66: live to a ripe old age | F66: iyice yaşlanana kadar yaşamak, çok uzun yaşamak
A67: 57 | B67: blow a gasket | C67: öfkelenmek, deliye dönmek | D67: 313 | E67: live up to all the hype | F67: yazıldığı/gösterildiği gibi çıkmak, beklenildiği gibi olmak
A68: 58 | B68: blow off some steam | C68: içini döküp rahatlamak | D68: 314 | E68: look down in the dumps | F68: çok neşesiz olmak,karadeniz'de gemileri batmış gibi durmak
A69: 59 | B69: blow your own trumpet | C69: (böbür böbür) böbürlenmek | D69: 315 | E69: look for a needle in a haystack | F69: samanlıkta iğne aramak
A70: 60 | B70: bone chilling | C70: tüyler ürpertici,korkutucu | D70: 316 | E70: look high and low (for someone or something) | F70: bakmadık yer bırakmamak,didik didik aramak
A71: 265 | B71: bone of contention | C71: ihtilaf konusu. anlaşmazlık sebebi | D71: 317 | E71: lose no time in doing something | F71: hemen/hiç vakit kaybetmeden (bir işe girişmek)
A72: 61 | B72: bottom line | C72: uzun lafın kısası,(asıl) önemli olan,sonuç | D72: 318 | E72: lose-lose situation | F72: kazanma ihtimali olmayan durum
A73: 62 | B73: bowl over | C73: ağzı bir karış açık kalmak, vurup devirmek | D73: 319 | E73: make a clean breast of | F73: itiraf etmek, içini boşaltmak, içini dökmek.
A74: 63 | B74: break it to…. | C74: birine kötü bir haber vermek | D74: 320 | E74: make a fool of | F74: rezil etmek,aptal durumuna düşürmek
A75: 64 | B75: bring something upon oneself | C75: kendi başına (dert) açmak | D75: 321 | E75: make a lucky guess | F75: şanslı bir tahmin yapmak
A76: 65 | B76: broad in the beam | C76: fıçı gibi,çok şişman | D76: 322 | E76: make a name for oneself | F76: isim yapmak, adından söz ettirmek
A77: 66 | B77: brood on | C77: kara kara düşünmek | D77: 323 | E77: make a pass at | F77: (birine) duyulan erotik hisleri belli etmek.
A78: 67 | B78: bum rap | C78: kötü şöhret | D78: 324 | E78: make fun of | F78: (bir kimse) ile alay etmek.
... A80: 69 | B80: burn someone at the stake | C80: yakarak öldürmek, birisini haşlamak | D80: 326 | E80: make head or tail of | F80: (bir şeyi) kavramaya çalışmak.(bir şeyi) anlamak
B81: burn someone in effigy | C81: protesto olarak sevilmeyen birinin kuklasını yakmak veya asmak. | D81: 327 | E81: make heavy weather of | F81: işi zora sokmak
A82: 70 | B82: bust up | C82: mahvetmek, parçalanmak | D82: 328 | E82: make much of somebody | F82: birisi için bayram yapmak, başının üstünde gezdirmek
A83: 71 | B83: buy one's way in to something | C83: bir şeyi para ile elde etmek | D83: 329 | E83: make no bones about | F83: açıkça söylemek.
A84: 72 | B84: buzz someone in | C84: (kapının düğmesine vb basarak) birisini bir yere/ içeri almak | D84: 330 | E84: make of | F84: yapmak,,,-den anlamak, -e anlam vermek,
A85: 73 | B85: by all accounts | C85: eldeki tüm verilere göre, herkesin dediğine göre | D85: 331 | E85: make the best of | F85: eldekini en iyi şekilde kullanmak
A86: 74 | B86: by same token | C86: aynı sebeple | D86: 332 | E86: make way | F86: yol açmak,yol vermek
A87: 75 | B87: call a spade a spade | C87: dobra dobra konuşmak, doğruya doğru eğriye eğri demek | D87: 333 | E87: man about town | F87: tiyatro ve gece kulübüne sıkça giden adam.
A88: 76 | B88: call in sick | C88: hastalık yüzünden işyerine gelmeyeceğini belirtmek | D88: 334 | E88: middle of the road | F88: ikisinin ortası
A89: 77 | B89: call it a night | C89: akşam olduğu için bir işe son vermek, paydos etmek | D89: 335 | E89: mind your own beeswax | F89: sen kendi işine bak
A90: 78 | B90: call over | C90: yoklama yapmak | D90: 336 | E90: murder on something | F90: bir şey için çok tahrip edici/zararlı olmak
A91: 79 | B91: call to mind | C91: hatırlamak; hatırlatmak, akla getirmek. | D91: 337 | E91: music to my ears | F91: duymak istediğim buydu!
A92: 80 | B92: can't stomach | C92: midesi kaldırmamak | D92: 338 | E92: near by | F92: el altında, çok yakında
A93: 81 | B93: can't stomach someone | C93: birini görmeye tahammül edememek | D93: 339 | E93: neck of the woods | F93: çevresinde, civarında
B94: case of something | C94: bir şeyin örneği | D94: 340 | E94: needless to say | F94: söylemeye gerek yok,fazla söze gerek yok
A95: 82 | B95: cast an eye | C95: göz gezdirmek | D95: 341 | E95: new-fangled | F95: yeni çıkmış,yeni
A96: 83 | B96: cast aspersions on | C96: iftira atmak,hakkında kötü ve olumsuz konuşmak | D96: 342 | E96: nip in the bud | F96: başlangıçta durdurmak veya bastırmak.
A97: 84 | B97: catch on | C97: moda olmak, tutmak. | D97: 343 | E97: of no avail | F97: boşuna.işe yaramaz
A98: 85 | B98: catch someone off guard | C98: birini gafil avlamak, birini hazırlıksız yakalamak | D98: 344 | E98: Off the books | F98: kayıt dışı
A99: 86 | B99: change one's tune | C99: ağız değiştirmek | D99: 345 | E99: off the charts | F99: alışılmışın dışında, standartların dışında
A100: 87 | B100: cheer up | C100: neşelenmek,neşelendirmek | D100: 346 | E100: off the mark | F100: yanlış/hedeften uzak
A101: 88 | B101: chew the cud | C101: geviş getirmek.derin derin düşünmek. | D101: 347 | E101: off the peg | F101: hazır giyim, al kullan
A102: 247 | B102: chime in with | C102: ile uyumlu olmak | D102: 348 | E102: off the track | F102: pistten/yoldan çıkmış,(konuyla) ilgisiz/alakasız
A103: 89 | B103: chuck down | C103: yere düşmek, kendini yerde bulmak | D103: 349 | E103: off the wagon | F103: (alkole/uyuşturucuya) tekrar başlamış
A104: 90 | B104: class up the joint | C104: bir şeyi daha şık/zarif hale getirmek | D104: 350 | E104: on cloud nine | F104: son derece mutlu
A105: 267 | B105: close at the hand | C105: çok yakın.yakın | D105: 351 | E105: on high | F105: yukarıda, yükse mevkide.cennette
A106: 91 | B106: close shave | C106: paçayı zor kurtarma. sinekkaydı tıraş | D106: 352 | E106: on the edge | F106: diken üstünde
A107: 92 | B107: coast-to-coast | C107: atlantik'ten pasifik'e,kıyıdan kıyıya | D107: 353 | E107: on the lam | F107: polisten/kanundan kaçan,kaçak
B108: cock of the walk | C108: bir yerde borusu öten kişi | D108: 354 | E108: on the off chance | F108: olur da ileride (...olur diye).ümidiyle
A109: 263 | B109: cold-shoulder | C109: birisine soğuk davranmak | D109: 355 | E109: on the rack | F109: son derece endişeli, çok kötü durumda
A110: 93 | B110: colour up | C110: renk katmak,daha ilginç kılmak | D110: 356 | E110: on the wane | F110: giderek azalmakta,azalmakta
A111: 94 | B111: come apart at the seams | C111: işler bozulmak, kötü duruma düşmek | D111: 357 | E111: on top form | F111: at gibi saglam :)
A112: 95 | B112: come at a price | C112: bir bedeli olmak | D112: 358 | E112: on top of | F112: ayrıca. -e ek olarak, -in yanı sıra, ile beraber:
A113: 96 | B113: come clean | C113: gerçeği bütün açıklığıyla söylemek, itiraf etmek | D113: 359 | E113: one in the eye for | F113: kulağına küpe
A114: 97 | B114: come in handy | C114: işe yaramak. (ileride) faydalı olmak | D114: 360 | E114: out and about | F114: hastalıktan kalkmış, iyileşmekte
A115: 98 | B115: come in useful | C115: yararlı olmak,işe yaramak | D115: 361 | E115: out in the open | F115: herkesin görebildiği (bir yerde), açık alanda
A116: 99 | B116: come straight out of a comic book | C116: çizgi romandan fırlamış gibi bir hali olmak | D116: 362 | E116: out of courtesy | F116: nezaketen/nezaket icabı
A117: 100 | B117: come to a halt | C117: durmak, durma noktasına gelmek | D117: 363 | E117: out of sorts | F117: keyifsiz,neşesiz
A118: 101 | B118: come to a head | C118: en yüksek noktaya gelmek, doruğa ulaşmak | D118: 364 | E118: out of the blue | F118: birden bire,aniden
B119: come to a standstill | C119: urma noktasına gelmek | D119: 365 | E119: out of the frying pan and into the fire | F119: yağmurdan kaçarken doluya tutulmak
A120: 102 | B120: come to fruition | C120: meyvesini vermek,sonuç vermeye başlamak | D120: 366 | E120: out of the woods | F120: artık tehlikede değil, kritik safhayı atlatmış
A121: 103 | B121: come unglued | C121: kendini kaybetmek,sinirleri boşanmak | D121: 367 | E121: out of whack | F121: bozuk, çalışamaz/işleyemez durumda.
A122: 104 | B122: come within a hair('s breadth) of someone or something | C122: çok yaklaşmak,ramak kalmak | D122: 368 | E122: over the moon | F122: çok mutlu,mutluluktan kendinden geçmiş
A123: 105 | B123: consecrate to | C123: adamak, varını yoğunu adamak | D123: 369 | E123: over the top | F123: çok abartılı,fazladan
A124: 106 | B124: cop out | C124: kaypaklık etmek, sözünden dönmek | D124: 370 | E124: pain the the neck | F124: baş belası,can sıkıcı tip
A125: 107 | B125: cozy up to someone | C125: biriyle sıkı fıkı olmak, samimileşmek | D125: 371 | E125: pale into insignificance | F125: diğerine göre önemsiz görünmek,önemli ya da anlamlı görünmemek
A126: 108 | B126: crack a joke | C126: espri patlatmak,şaka yapıyor | D126: 372 | E126: pan down | F126: (emeğin) boşa gitmesi
A127: 109 | B127: crack open | C127: yarılmak, çatlamak | D127: 373 | E127: pass the hat around | F127: (bir gruptan vb.) para toplamak
A128: 110 | B128: crack open a bottle | C128: (kutlama amacıyla) bir şişe açmak | D128: 374 | E128: pay off | F128: (borcu) tamamıyla ödemek.
A129: 111 | B129: crap out of something on someone | C129: (özellikle korktuğundan dolayı) bir işten elini eteğini çekmek, başlanan işi bitirmeyerek birini baltalamak/sabote etmek | D129: 375 | E129: peace of mind | F129: iç rahatlığı, gönül rahatlığı
A130: 112 | B130: credit someone with | C130: sevilmeyen birinde olumlu bir niteliğin olduğunu kabul etmek | D130: 376 | E130: pep talk | F130: cesaret konuşması, moral konuşması
A131: 113 | B131: culminate in | C131: ile sonuçlanmak, ile sona ermek, ile son bulmak. sebep olmak | D131: 377 | E131: pick somebody's brain | F131: fikir sormak/istemek, bir kişinin görüş ve düşüncelerini sormak
... A135: 117 | B135: cut it close | C135: ucu ucuna/milimi milimine yapmak/yetişmek | D135: 381 | E135: place the blame on someone | F135: suçu başkasının üzerine atmak, birisini suçlamak
B136: cut no ice | C136: (birini) etkilemeyi başaramamak | D136: 382 | E136: play it by ear | F136: duruma göre hareket etmek
A137: 118 | B137: cut someone to ribbons | C137: bozguna uğratmak, birini ciddi/ağır biçimde kesmek | D137: 383 | E137: play it by the book | F137: kitabına göre oynamak
A138: 119 | B138: cut to the chase | C138: doğrudan sonuca gitmek, sadede gelmek | D138: 384 | E138: played out | F138: modası geçmiş,bitkin,işe yaramaz
A139: 121 | B139: devil of a job | C139: en zor iş/görev,deveye hendek atlatmaktan daha zor | D139: 386 | E139: plead with someone for something | F139: (bir şey için) birisine yalvarmak
...

Sheet phrasal verb
A1: Phrasal verbs
A2: word | B2: meaning | C2: word | D2: meaning | E2: word | F2: meaning
A3: abide by | B3: ..-e uymak, -e riayet etmek. | C3: go by | D3: geçmek,göre hareket etmek, kılavuz saymak | E3: ride out | F3: sağ salim çıkmak
A4: account for | B4: hesap vermek, açıklamak | C4: go down | D4: inmek,(iş vb) batmak | E4: ride up | F4: yukarı çıkmak
A5: act on | B5: etkilemek | C5: go down on | D5: oral seks yapmak | E5: rig out | F5: süslenip püslenmek
A6: act out | B6: (rol) canlandırmak | C6: go for | D6: tercih etmek,dışarı çıkmak,hoşlanmak | E6: rig up | F6: uyduruvermek
A7: act up | B7: yaramazlık yapmak,gösteriş yapmak. | C7: go in | D7: içeriye girmek,içeri girmek | E7: rile up | F7: sinirlendirmek
A8: add up | B8: toplamak,makul olmak, akla yakın olmak. | C8: go in for | D8: bir şeyi yapmaktan hoşlanmak,bir şeyin meraklısı olmak | E8: ring off | F8: telefonu kapamak
A9: add up to | B9: -e varmak, (bir yekûn) tutmak.anlamına gelmek: | C9: go into | D9: girmek, girmek (konuşmaya-tartışmaya) | E9: rip off | F9: kazık atmak, kazıklamak
A10: after careful thought | B10: iyice düşündükten sonra | C10: go loco | D10: delirmek, balatayı yakmak | E10: roll away | F10: yuvarlanarak ilerlemek
A11: after math | B11: kötü sonuç,kötü yan etki | C11: go off | D11: .. -den hoşlanmamaya başlamak.patlamak. geçmek (bir olay belirli bir şekilde) | E11: roll on | F11: yuvarlanmak
A12: all but | B12: hemen hemen,neredeyse | C12: go off on one | D12: kendini kaybetmek, kontrolü kaybetmek | E12: roll out | F12: sunmak,ilk kez görücüye çıkarılmak
A13: amp up | B13: güçlendirmek, arttırmak | C13: go on | D13: Devam etmek,Olmak, meydana gelmek | E13: roll up | F13: sıvamak,toplanmak
... A449: go away | B449: gitmek, ayrılmak. | C449: rely upon | D449: bel bağlamak,güvenmek | E449: hollow out | F449: çukur açmak.kazmak
A450: go back | B450: Geri dönmek | C450: remark on someone | D450: biri hakkında yorumda bulunmak
A451: go back over | B451: tekrar/yeniden gözden geçirmek/incelemek | C451: rev up | D451: hızlandırmak
A452: go behind | B452: peşine takılıp gitmek | C452: ride off | D452: atını sürerek gitmek

Sheet conjunction
A1: Conjunction
A2: word | B2: meaning | C2: word | D2: meaning | E2: word | F2: meaning
A3: according as | B3: .-dikçe, tıpkı ,,-diği gibi | C3: except | D3: haricinde,dışında | E3: on the contrary | F3: aksine
A4: accordingly | B4: bu doğrultuda,buna göre | C4: except if | D4: . -mesinin dışında | E4: on the grounds that | F4: ...-e dayanarak
A5: actually | B5: aslında, gerçekten | C5: for fear that | D5: korkusu ile | E5: on the other hand | F5: öte yandan
A6: additionally | B6: ek olarak ,ayrıca | C6: for that reason that | D6: işte bu sebepten ötürü | E6: on the pretext that | F6: bahanesiyle
A7: after | B7: ...-den sonra, ardından | C7: for the reason that | D7: sebebiyle | E7: once | F7: bir zamanlar,bir kere,-ir -mez
A8: after which | B8: ..-mesinden sonra.-den sonra | C8: from which | D8: oradan , -den | E8: one would think that | F8: güya
A9: afterwards | B9: ardından | C9: furthermore | D9: bundan başka, ayrıca. | E9: one would wish that | F9: gönül ister ki
A10: Albeit | B10: ... de olsa:gerçi,hernekadar,isede | C10: given that | D10: tahminen, farz edelim ki | E10: only if | F10: tek şartla
A11: also | B11: ayrıca,hemde -de, -da | C11: hence | D11: bu yüzden | E11: or | F11: veya, ya da, aksi takdirde
A12: although yet | B12: her ne kadar olsa da | C12: however | D12: ancak,fakat,her nasılsa | E12: or else | F12: aksi takdirde
A13: although/though | B13: ….-e rağmen/rağmen | C13: however much | D13: ne kadar olursa olsun | E13: otherwise | F13: aksi takdirde
... A54: even when | B54: ...-dığı zaman bile | C54: on condition that | D54: koşuluyla,şartıyla | E54: yet more | F54: hatta bundan daha fazla, hatta

Sheet prepositional phrases
A1: Prepositional phrases
A2: word | B2: meaning | C2: word | D2: meaning | E2: word | F2: meaning
A3: a diversity of | B3: birçok farklı | C3: in advance of | D3: öncesinde,-in önünde | E3: in view of | F3: ..den dolayı, göz önüne alarak
A4: a good deal of | B4: birçok | C4: in aid of | D4: menfaatine, -e yardım için. | E4: in wake of | F4: izini takip ederek,peşinde
A5: a great deal of | B5: ..çok, bir hayli | C5: in an attempt to | D5: .mak için. mek için, amacıyla | E5: including | F5: dahil
A6: a large amount of | B6: çok miktarda | C6: in an effort to | D6: amacıyla, mak için, mek için | E6: inside of | F6: dahilinde, -in içinde
A7: a large quantity of | B7: çok miktarda | C7: in and around | D7: içinde ve çevresinde | E7: instead of | F7: ...ın yerine
A8: a number of | B8: birkaç, bir çok | C8: in anticipation of | D8: bir şeyin gerçekleşebileceği düşüncesiyle | E8: irrespective of | F8: ...e bakılmaksızın
A9: a range of | B9: bir dizi | C9: in between | D9: arasında, aralarında | E9: just like | F9: gibi
A10: a variety of | B10: bir çok farklı | C10: in case of | D10: ...ın durumunda | E10: less than | F10: ...den az
A11: a whole bunch of | B11: bir sürü | C11: in commemoration of | D11: anısına | E11: mindless of | F11: .e aldırış etmeyen
A12: a wide range of | B12: bir çok farklı | C12: in common with | D12: ile ortak olarak | E12: more than | F12: ...den fazla
A13: according to | B13: ...e göre | C13: in company with | D13: ile beraber, birlikte. | E13: next to | F13: .-in yanında, -e bitişik; -in yakınındaki.
... A34: as per | B34: gereğince,uyarınca, göre | C34: in particular | D34: özellikle, bilhassa | E34: opposite to | F34: . -e karşı,-e muhalif
C35: in place of | D35: ...ın yerine | E35: other than | F35: ..den başka
A36: as regards | B36: ..gelince, ile ilgili | C36: in point of | D36: hususunda, bakımından | E36: out of keeping with | F36: ile uyumsuz olarak
A37: as such in | B37: . -de olduğu gibi | C37: in preference to | D37: . -e tercihen,öncelikle | E37: outside of | F37: dışında, haricinde
A38: as to | B38: ...e dair, -ile ilgili | C38: in prospect of | D38: varsayımıyla | E38: over and above | F38: yanında,üstelik,-den ayrı olarak, -den başka.
A39: as to whether | B39: olup olmadığına gelince, olup olmadığı konusunda | C39: in pursuance of | D39: yerine getirirken, peşinde koşarken, gerçekleştirmeye çalışırken | E39: owing to | F39: ...den dolayı
A40: as well | B40: ...de , -da | C40: in pursuant of | D40: uygun olarak,göre | E40: partial to | F40: meyilli, -e taraftar
A41: as well as | B41: ...ve de, yanısıra,yanısıra | C41: in pursuit of | D41: peşinde, arayışta | E41: pertaining to | F41: ile ilgili
A42: as with | B42: ...-da olduğu gibi | C42: in recognition of | D42: bakımından, tanınmasıyla | E42: prior to | F42: ...den önce
A43: as yet | B43: şimdiye kadar, henüz | C43: in reference to | D43: ..-e dair, -e ilişkin,nazaran | E43: pursuant to | F43: .-e göre.-e uygun olarak
A44: aside from | B44: dışında, -den başka | C44: in regard to | D44: .-e gelince. -e göre | E44: ranging from | F44: . -den tutun da, -den -e uzanan
A45: astern of | B45: .-den arkaya,arkada | C45: in relation to | D45: hakkında. - e ilişkin olarak | E45: rather than | F45: ..den ziyade
A46: at least | B46: en azından, hiç olmazsa | C46: in respect of | D46: dair,hakkında,hususunda | E46: regardless of | F46: ...e bakılmaksızın
A47: at odd | B47: arası açık olmak | C47: in response to | D47: ...e karşılık olarak | E47: related to | F47: ile ilgili
... A83: in accordance with | B83: ..e paralel olarak | C83: in trust | D83: gözetiminde | E83: within the scope of | F83: kapsamında, çerçevesinde
A84: in addition to | B84: ...e ilaveten

Sheet oxford 3000
C2: a | D2: (herhangi) bir | E2: a book, a car , a movie (bir kitap, bir araba, bir film)
B3: * | C3: abandon | D3: terk etmek, bırakmak, vazgeçmek, yüzüstü bırakmak | E3: The children have been abandoned by their mother. (Çocuklar anneleri tarafından terk edildi.)
C4: abandoned | D4: terk edilmiş, terk, Vazgeçilen | E4: Sen de kendini terk edilmiş hissetmişsin. You felt they'd abandoned you.
C5: ability | D5: yetenek, beceri, kabiliyet, hüner | E5: She has some musical ability. (Onun biraz müzik yeteneği var.)
C6: able | D6: yetenekli, hünerli, yapabilen, becerikli, | E6: You must be able to speak German for this job. (Bu iş için Almanca konuşuyor olabilmelisin.)
C7: unable | D7: aciz, yapamaz, gücü yetmez | E7: I tried to contact him but was unable to. (Onunla irtibat kurmaya çalıştım ama olmadı.)
C8: about | D8: üzere, yaklaşık, hemen hemen,aşağı yukarı, hakkında (ed.) | E8: I was very sorry to hear about your sister. (Kardeşin hakkında duyduklarıma çok üzüldüm.)
C9: above | D9: zf; üzerine, yukarıda, üstünde ,üzerinde s.; yukarıdaki, yukarıda geçen | E9: The birds were flying above the clouds. (Kuşlar bulutların üstünde uçuyorlardı.)
C10: abroad | D10: zf.; yurt dışında s.; dışarı, dış ülke , yurt dışı | E10: She worked abroad for a year. ( Bir yıl yurt dışında yaşadı.)
C11: absence | D11: bulunmama, yokluk, olmayış | E11: They didn’t notice his absence. (Onun yokluğunu fark etmediler.)
C12: absent | D12: yok, bulunmuyor, olmama | E12: Typical human behavior is now entirely absent. *İnsana özgü davranışlar, artık tamamen yok.
B13: * | C13: absolute | D13: i. ;mutlak s.; salt,mutlak, kati, kesin | E13: I want absolute silence during the lesson. (Ders süresince mutlak sessizlik istiyorum.)
C14: absolutely | D14: kesinlikle, mutlaka, tamamıyla, muhakkak | E14: It is absolutely an extraordinary situation. (Bu kesinlikle olağanüstü bir durum.)
B15: * | C15: absorb | D15: emmek,içine çekmek, soğurmak, özümsemek, anlamak | E15: Plants absorb oxygen. (Bitkiler oksijen emer.)
B16: * | C16: abuse | D16: i.; suistimal, taciz f.; suistimal etmek, kötüye kullanmak, | E16: She suffered years of physical abuse. (Yıllarca fiziksel tacize uğradı.)
C17: academic | D17: i.; öğretim görevlisi s.; akademik, bilimsel | E17: The new academic year starts in October. (Yeni akademik yıl ekim ayında başlıyor.)
C18: accent | D18: aksan, vurgu, şive | E18: She spoke English with an accent.
C19: accept | D19: kabul etmek, kabullenmek, onaylamak | E19: She has decided not to accept the job. ( İşi kabul etmemeye karar verdi.)
C20: acceptable | D20: kabul edilebilir acceptable, reasonable, palatable, admissible | E20: Not an acceptable mistake. Kabul edilebilir bir hata değil.
B21: * | C21: access | D21: i.; erişme, erişim, giriş f.; erişmek, | E21: You need a password to access the confidential information. (Gizli bilgilere erişmek için bir şifren olması gerek.)
C22: accident | D22: kaza , arıza, rastlantı, beklenmedik olay, kazara | E22: The accident happened at 5 a.m. (Kaza sabah saat 5’te oldu.)
C23: by accident | D23: kaza ile | E23: We met by accident at the airport.
C24: accidental | D24: kaza sonucu | E24: There would be the mandatory accidental damage insurance. zorunlu kaza sonucu hasar sigortası olacaktı.
C25: accidentally | D25: yanlışlıkla **inadvertently, mistakenly, inadvertent, erroneously | E25: I accidentally grabbed your book. Yanlışlıkla senin kitabını almışım.
C26: accompany | D26: eşlik etmek, yanında olmak, , arkadaşlık etmek, yoldaşlık etmek | E26: Her husband accompanied her on the trip. (Gezide kocası ona eşlik etti.)
C27: according | D27: i.; uyma f.; uyarak, uygun olarak, -e göre, birseye bagli olarak | E27: Everything went according to his instructions. (Her şey onun talimatlarına uygun olarak ilerledi.)
C28: account | D28: i.; hesap , hesap verme f.; açıklamak, hesap vermek, saymak | E28: I don’t have a bank account. (Banka hesabım yok.)
B29: * | C29: accurate | D29: kesin, doğru, tam, hatasız, dakik | E29: This watch is not very accurate. (Bu saat çok doğru değil.)
C30: accurately | D30: doğru *right, true, correct, towards, correctly, | E30: Science can predict accurately when a new moon rises. Bilim yeni ay doğumunu tam doğru olarak tahmin edebilir.
B31: * | C31: accuse | D31: suçlamak, suçlamada bulunmak, itham etmek | E31: He accused him of lying. ( Onu yalan söylemekle suçladı.)
C32: achieve | D32: başarmak, elde etmek, ulaşmak, üstesinden gelmek | E32: He had finally achieved great success. (Sonunda büyük başarı elde etti.)
C33: achievement | D33: başarı, başarma, elde etme,kazanım | E33: It was a remarkable achievement for such a young student. (Bu, böylesine genç bir öğrenci için olağanüstü bir başarıydı.)
C34: acid | D34: i.; asit, ekşime s.; ekşi | E34: Acid can damage things. (Asit zarar verebilir.)
B35: * | C35: acknowledge | D35: kabul etmek, kabullenmek, tasdik etmek, beyan etmek | E35: It is generally acknowledged to be wrong. (Bu genel olarak yanlış olarak kabul edilir.)
B36: * | C36: acquire | D36: elde etmek, edinmek, kazanmak, sahip olmak | E36: She has acquired a good knowledge of History. (Tarih konusunda iyi derecede bilgi sahibi oldu.)
C37: across | D37: f.; boydan boya geçmek ed.; karşısında zf.;karşıdan karşıya | E37: The hospital is right across the bank. (Hastane bankanın tam karşısında.)
C38: act | D38: f.; davranmak, hareket etmek, rol oynamak, yalandan yapmak i.; yasa, eylem | E38: Don’t act like sorry. (Üzgünmüş gibi davranma.)
C39: action | D39: eylem, aksiyon, dava, fiil, davranış | E39: Everyone must take responsibility for their actions. (Herkes davranışlarının sorumluluğunu almalı.)
C40: take action | D40: #N/A | E40: #N/A
C41: active | D41: etkin, faal, aktif, çalışkan | E41: She takes an active part in this project. (Bu projede aktif rol alıyor.)
C42: actively | D42: #N/A | E42: #N/A
C43: activist | D43: aktivist, eylemci | E43: The human rights activists are organizing a demonstration this week. (İnsan hakları aktivistleri bu hafta bir eylem düzenliyor.)
C44: activity | D44: etkinlik, faaliyet, işlem, fiil | E44: The club provides a wide variety of activities. (Klüp çok çeşitli aktiviteler sunmaktadır.)
C45: actor | D45: oyuncu, erkek oyuncu, aktör,artist, | E45: He is a world famous actor. (Dünyaca ünlü bir aktördü.)
C46: actual | D46: asıl, gerçek, hakiki, doğru, aktüel | E46: The actual cost was higher than he expected. (Gerçek tutar beklediğinden daha yüksekti.)
C47: actually | D47: aslında, fiilen, gerçekte, sahiden | E47: What did he actually say? (Gerçekten ne söyledi?)
B48: * | C48: ad | D48: reklam, ilan, duyuru | E48: We put an ad in the local newspaper. (Yererl gazeteye reklam verdik.)
C49: advertisement | D49: #N/A | E49: #N/A
C50: adapt | D50: adapte etmek, adapte olmak, uyarlamak, uymak, uyum sağlamak | E50: We should adapt quickly to the new system. (Yeni sisteme hızlıca uyum sağlamalıyız.)
C51: add | D51: eklemek, ilave etmek, katmak , toplamak | E51: Do you want to add your name to the list? (İsmini listeye eklemek ister misin)
C52: addition | D52: ek, ekleme, ilave, toplama, katma , eklenti | E52: The last additions were done last night. (Son eklemeler dün gece yapıldı.)
C53: in addition | D53: #N/A | E53: #N/A
C54: additional | D54: ek , ilave, ilaveten | E54: The company provided an additional 5 million dollars to this project.( Şirket, bu proje için ilave olarak 5 milyon dolar sağladı.)
C55: address | D55: f.; hitap etmek, konuşma yapmak, göndermek, değinmek, adres yazmak i.; adres, söylev, hitap, konuşma, speech | E55: I gave my address and phone number. (Adresimi ve telefon numaramı verdim.)
B56: * | C56: adequate | D56: yeterli, uygun, kafi | E56: There is not an adequate supply of water in Africa. (Afrika’da yeterli su tedariği bulunmamakta.)
C57: adequately | D57: #N/A | E57: #N/A
B58: * | C58: adjust | D58: ayarlamak, uydurmak, uyarlamak, adapte olmak, | E58: I couldn’t adjust to living alone. (Yalnız yaşamaya uyum sağlayamadım.)
C59: administration | D59: yönetim, idare, yöneticilik, idarecilik | E59: The school administration will organize a picnic at the weekend. ( Okul yönetimi hafta sonu bir piknik organize edecek.)
C60: admiration | D60: #N/A | E60: #N/A
B61: * | C61: admire | D61: hayran olmak, beğenmek, | E61: I really admire your recent works. (Son çalışmalarınıza gerçekten hayranım.)
B62: * | C62: admit | D62: itiraf etmek, kabul etmek, izin vermek, teslim etmek | E62: Don’t be afraid to admit your mistakes. (Hatalarını itiraf etmekten korkma.)
C63: adopt | D63: evlat edinmek, benimsemek, kabul etmek, sahiplenmek | E63: A childless couple has adopted a baby. (Çocuğu olmayan çift, bir bebek evlat edindi.)
C64: adult | D64: i.; yetişkin s.; ergin, yetişkin | E64: Why don’t you act like an adult? (Neden bir yetişkin gibi hareket etmiyorsun?)
B65: * | C65: advance | D65: f.; ilerlemek, geliştirmek, gelişim göstermek i.; ilerleme, terfi | E65: Do you follow the recent advances in medical science? ( Tıp alanındaki son gelişmeleri takip ediyor musun?)
C66: advanced | D66: ileri, gelişmiş, ileri derecede | E66: England is an industrially advanced country. (İngiltere sanayi bakımından gelişmiş bir ülkedir.)
C67: in advance | D67: #N/A | E67: #N/A
C68: advantage | D68: yarar, fayda, avantaj, | E68: You will have an advantage if you prepare well. (Eğer iyi hazırlanırsan avantajın olacak.)
C69: take advantage of | D69: #N/A | E69: #N/A
C70: adventure | D70: i.; macera , serüven, risk f.; tehlikeye atmak, riske atmak | E70: She likes reading adventure stories. (Macera hikayeleri okumayı sever.)
C71: advertise | D71: #N/A | E71: #N/A
C72: advertising | D72: reklam, tanıtım, reklamcılık | E72: Alcohol advertising has been banned. (Alkol reklamı yasaklandı.)
C73: advertisement | D73: #N/A | E73: #N/A
C74: advice | D74: öğüt, nasihat, tavsiye,danışma | E74: I will give you some advice for this job. ( Sana bu iş için biraz tavsiye vereceğim.)
C75: advise | D75: öğüt vermek, nasihat etmek, tavsiyede bulunmak, danışmak | E75: I advise you to be careful. (Size dikkatli olmanızı tavsiye ederim)
B76: * | C76: affair | D76: mesele, vaka, ilişki | E76: She is having an affair with her colleague . (Meslektaşıyla ilişkisi var.)
C77: affect | D77: i.; duygulanım, heyecan f.; etkilemek, duygulandırmak, gibi davranmak | E77: Her opinions affected my decision. (Onun görüşleri kararımı etkiledi.)
C78: affection | D78: #N/A | E78: #N/A
B79: * | C79: afford | D79: satın almaya gücü yetmek, maddi gücü yetmek | E79: We can’t afford to go holiday this summer. (Bu yaz tatile gitmeye maddi gücümüz yetmez.)
C80: afraid | D80: korkmuş, ürkmüş | E80: Are you afraid of darkness? (Karanlıktan korkar mısın?)
C81: after | D81: #N/A | E81: #N/A
C82: afternoon | D82: öğleden sonra | E82: I have a meeting on Monday afternoon. (Pazartesi öğleden sonra topantım var.)
C83: afterward | D83: #N/A | E83: #N/A
C84: again | D84: tekrar, yeniden, bir daha | E84: Can you say again? I couldn’t understand. (Tekrar söyler misin? Anlayamadım.)
C85: against | D85: ed.; karşı , aykırı, aleyhinde zf.; -e doğru, ters olarak | E85: That’s against the law. (Bu yasaya aykırı.)
C86: age | D86: i.; yaş, çağ f.; yaşlanmak,eskimek | E86: When I was your age, I was already finished school. (Senin yaşındayken okulu çoktan bitirmiştim.)
C87: aged | D87: #N/A | E87: #N/A
C88: agency | D88: acenta, ajans | E88: We are working with the local travel agancy. (Yerel seyehat acentası ile çalışıyoruz.)
B89: * | C89: agenda | D89: gündem, gündemde olan konular , ajanda | E89: Did you have any information about the meeting’s agenda? ( Toplantının gündemi hakkında bilgin var mı?)
C90: agent | D90: acente, temsilci, ajan, vekil | E90: Did you call the travel agent? (Seyehat acentasını aradın mı?)
C91: aggressive | D91: agresif, saldırgan, kavgacı | E91: She gets aggressive when she’s hungry. (Acıkınca agresifleşiyor.)
C92: ago | D92: önce | E92: I went to Spain a long time ago. (İspanya’ya çok uzun zaman önce gittim.)
C93: agree | D93: aynı fikirde olmak, kabul etmek, hemfikir olmak , mutabık omak | E93: Sometimes I agree with her ideas. (Bazen onun görüşleriyle aynı fikirde oluyorum)
C94: agreement | D94: anlaşma, sözleşme, uzlaşma, mutabakat | E94: The agreement was signed by the member countries. (Anlaşma, üye ülkeler tarafından imzalandı.)
C95: ahead | D95: zf.; ilerde, leriye s.; öndeki | E95: I will walk ahead. (İleriye yürüyeceğim)
B96: * | C96: aid | D96: i.; yardım , yardımcı f.; yardım etmek, | E96: I joined a medical aid programme. (Tıbbi yardım programına katıldım)
C97: aim | D97: i.; hedef, amaç f.; amaçlamak , hedeflemek | E97: His main aim in life is to earn a lot of money. (Onun hayattaki asıl hedefi çok para kazanmak.)
C98: air | D98: i.; hava f.; havalandırmak – to be on air : yayında olmak | E98: I need some fresh air, let’s go out. (Biraz temiz havaya ihtiyacım var, haydi dışarı çıkalım.)
C99: aircraft | D99: uçak, hava taşıtı | E99: This aircraft can carry 300 people. (Bu uçak 300 kişi taşıyabilir.)
C100: airport | D100: havalimanı, havaalanı | E100: We should get to the airport before the flight time. (Uçuş zamanından önce havaalanında olmalıyız.)
C101: alarm | D101: #N/A | E101: #N/A
...

Sheet 3000
A2: 1 | C2: 1- a
A3: 2 | C3: (herhangi) bir
A4: 3 | C4: a book, a car , a movie (bir kitap, bir araba, bir film)
A5: 4
A6: 5 | B6: * | C6: 2-abandon ; (fiil)
A7: 6 | C7: terk etmek, bırakmak, vazgeçmek, yüzüstü bırakmak
A8: 7 | C8: The children have been abandoned by their mother. (Çocuklar anneleri tarafından terk edildi.)
A9: 8
A10: 9 | C10: 3-ability; (isim)
A11: 10 | C11: yetenek, beceri, kabiliyet, hüner
A12: 11 | C12: She has some musical ability. (Onun biraz müzik yeteneği var.)
A13: 12
A14: 13 | C14: 4-able; (sıfat)
A15: 14 | C15: yetenekli, hünerli, yapabilen, becerikli,
A16: 15 | C16: You must be able to speak German for this job. (Bu iş için Almanca konuşuyor olabilmelisin.)
A17: 16
A18: 17 | B18: * | C18: 5-abortion; (isim)
A19: 18 | C19: kürtaj, bebek aldırma,çocuk düşürme
A20: 19 | C20: She decided to have an abortion. (O, kürtaj yaptırmaya karar verdi.)
A21: 20 | C21: a woman’s right to abortion
A22: 21 | C22: the country's strict abortion laws
A23: 22 | C23: I've always been anti-abortion.
A24: 23
A25: 24 | C25: 6- about; (zarf, edat)
A26: 25 | C26: üzere, yaklaşık, hemen hemen,aşağı yukarı, hakkında (ed.)
A27: 26 | C27: I was very sorry to hear about your sister. (Kardeşin hakkında duyduklarıma çok üzüldüm.)
A28: 27
A29: 28 | C29: 7- above; (zarf, sıfat)
A30: 29 | C30: zf; üzerine, yukarıda, üstünde ,üzerinde s.; yukarıdaki, yukarıda geçen
A31: 30 | C31: The birds were flying above the clouds. (Kuşlar bulutların üstünde uçuyorlardı.)
A32: 31
A33: 32 | C33: 8- abroad; zarf, sıfat) ---aboard: gemi, ucak vs icinde
A34: 33 | C34: zf.; yurt dışında s.; dışarı, dış ülke , yurt dışı
A35: 34 | C35: She worked abroad for a year. ( Bir yıl yurt dışında yaşadı.)
A36: 35
A37: 36 | C37: 9- absence; (isim)
A38: 37 | C38: bulunmama, yokluk, olmayış
A39: 38 | C39: They didn’t notice his absence. (Onun yokluğunu fark etmediler.)
A40: 39
A41: 40 | B41: * | C41: 10) absolute; (isim, sıfat)
A42: 41 | C42: i. ;mutlak s.; salt,mutlak, kati, kesin
A43: 42 | C43: I want absolute silence during the lesson. (Ders süresince mutlak sessizlik istiyorum.)
A44: 43
A45: 44 | C45: 11) absolutely; (zarf)
A46: 45 | C46: kesinlikle, mutlaka, tamamıyla, muhakkak
A47: 46 | C47: It is absolutely an extraordinary situation. (Bu kesinlikle olağanüstü bir durum.)
A48: 47
A49: 48 | B49: * | C49: 12) absorb; (fiil)
A50: 49 | C50: emmek,içine çekmek, soğurmak, özümsemek, anlamak
A51: 50 | C51: Plants absorb oxygen. (Bitkiler oksijen emer.)
A52: 51 | C52: to take in a liquid, gas or other substance from the surface or space around
A53: 52 | C53: Let the rice cook until it has absorbed all the water.
A54: 53 | C54: The cream is easily absorbed into the skin.
A55: 54
A56: 55 | B56: * | C56: 13) abuse; (isim, fiil)
C57: i.; suistimal, taciz f.; suistimal etmek, kötüye kullanmak,
C58: She suffered years of physical abuse. (Yıllarca fiziksel tacize uğradı.)
C59: the use of something in a way that is wrong or harmful SYNONYM misuse
C60: alcohol/drug abuse
C61: The system of paying cash bonuses is open to abuse (= might be used in the wrong way).
C62: The legal system is open to abuse.
A63: 62
A64: 63 | B64: * | C64: 14) academic; (isim, sıfat)
A65: 64 | C65: i.; öğretim görevlisi s.; akademik, bilimsel
A66: 65 | C66: The new academic year starts in October. (Yeni akademik yıl ekim ayında başlıyor.)
A67: 66
A68: 67 | C68: 15) accept; (fiil)
A69: 68 | C69: kabul etmek, kabullenmek, onaylamak
A70: 69 | C70: She has decided not to accept the job. ( İşi kabul etmemeye karar verdi.)
A71: 70
A72: 71 | B72: * | C72: 16) access; (isim, fiil)
A73: 72 | C73: i.; erişme, erişim, giriş f.; erişmek,
A74: 73 | C74: You need a password to access the confidential information. (Gizli bilgilere erişmek için bir şifren olması gerek.)
A75: 74
A76: 75 | C76: 17) accident; (isim)
A77: 76 | C77: kaza , arıza, rastlantı, beklenmedik olay, kazara
A78: 77 | C78: The accident happened at 5 a.m. (Kaza sabah saat 5’te oldu.)
A79: 78
A80: 79 | C80: 18) accompany; (fiil)
A81: 80 | C81: eşlik etmek, yanında olmak, , arkadaşlık etmek, yoldaşlık etmek
A82: 81 | C82: Her husband accompanied her on the trip. (Gezide kocası ona eşlik etti.)
A83: 82
A84: 83 | B84: * | C84: 19) accomplish; (fiil)
A85: 84 | C85: başarıyla tamamlamak, becermek, sonuçlandırmak, üstesinden gelmek
A86: 85 | C86: Mission accomplished. (Görev başarıyla tamamlandı.)
A87: 86 | C87: The first part of the plan has been safely accomplished.
A88: 87 | C88: I don't feel I've accomplished very much today.
A89: 88
A90: 89 | C90: 20) according; (isim, zarf)
A91: 90 | C91: i.; uyma f.; uyarak, uygun olarak, -e göre, birseye bagli olarak
A92: 91 | C92: Everything went according to his instructions. (Her şey onun talimatlarına uygun olarak ilerledi.)
A93: 92
A94: 93 | C94: 21) account; (isim, fiil)
A95: 94 | C95: i.; hesap , hesap verme f.; açıklamak, hesap vermek, saymak
A96: 95 | C96: I don’t have a bank account. (Banka hesabım yok.)
A97: 96
A98: 97 | B98: * | C98: 22) accurate; (sıfat)
A99: 98 | C99: kesin, doğru, tam, hatasız, dakik
A100: 99 | C100: This watch is not very accurate. (Bu saat çok doğru değil.)
A101: 100
...

Sheet Rating
B4: the | C4: 1
B5: be | C5: 2
B6: and | C6: 3
B7: of | C7: 4
B8: a | C8: 5
B9: in | C9: 6
B10: to | C10: 7
B11: have | C11: 8
B12: to | C12: 9
B13: it | C13: 10
B14: I | C14: 11
B15: that | C15: 12
... B494: arm | C494: 492
B495: TRUE | C495: 493
B496: federal | C496: 494
B497: break | C497: 495
B498: better | C498: 496
B499: difference | C499: 497
B500: thank | C500: 498
B501: receive | C501: 499
B502: value | C502: 500
B503: international | C503: 501
B504: building | C504: 502
B505: action | C505: 503
B506: full | C506: 504
B507: model | C507: 505
... B2649: aggressive | C2649: 2538
B2650: FALSE | C2650: 2539
B2651: intention | C2651: 2540
B2652: channel | C2652: 2541
B2653: extreme | C2653: 2542
B2654: tube | C2654: 2543
B2655: drawing | C2655: 2544
B2656: protein | C2656: 2545
B2657: quit | C2657: 2546
B2658: absence | C2658: 2547
B2659: roll | C2659: 2548
B2660: Latin | C2660: 2549
B2661: rapidly | C2661: 2550
B2662: jail | C2662: 2551
... B5120: till | C5120: 5000
